bowentese1/__init__.py
bowentese1/__main__.py
bowentese1/main.py
bowentest1-0.1.11.dist-info/METADATA
bowentest1-0.1.11.dist-info/WHEEL
bowentest1-0.1.11.dist-info/entry_points.txt
bowentest1-0.1.11.dist-info/top_level.txt
bowentest1-0.1.11.dist-info/RECORD
