Metadata-Version: 2.4
Name: bowentest1
Version: 0.1.11
Summary: 测试mcp项目
Requires-Python: >=3.11
Requires-Dist: httpx>=0.28.1
Requires-Dist: mcp>=1.6.0
